{
  "collapse-filter": false,
  "search": "path:\"2023/book/高中_教科书/政治/秦宣_朱明光.(2023).中国特色社会主义 _必修一_中国特色社会主义\"",
  "showTags": false,
  "showAttachments": false,
  "hideUnresolved": false,
  "showOrphans": true,
  "collapse-color-groups": false,
  "colorGroups": [],
  "collapse-display": false,
  "showArrow": false,
  "textFadeMultiplier": 0,
  "nodeSizeMultiplier": 1,
  "lineSizeMultiplier": 1,
  "collapse-forces": false,
  "centerStrength": 0.518713248970312,
  "repelStrength": 10,
  "linkStrength": 1,
  "linkDistance": 250,
  "scale": 0.7023319615912207,
  "close": true
}